japtkpy/__init__.py
japtkpy/res/model_ja.min.json
japtkpy/src/__init__.py
japtkpy/src/tokenizer/__init__.py
japtkpy-0.0.5.dist-info/METADATA
japtkpy-0.0.5.dist-info/WHEEL
japtkpy-0.0.5.dist-info/top_level.txt
japtkpy-0.0.5.dist-info/RECORD
