Metadata-Version: 2.1
Name: japtkpy
Version: 0.0.5
Summary: A simple Japanese Language Tokenizer
Home-page: https://github.com/sherryt400/japtkpy
Author: Sheharyar Naseem
Author-email: sherryfbi1994@gmal.com
License: UNKNOWN
Platform: UNKNOWN
Classifier: Programming Language :: Python :: 3
Classifier: License :: OSI Approved :: MIT License
Classifier: Operating System :: OS Independent
Requires-Dist: rakutenma (==0.3.3)
